[
  {
    "owner": "linuxserver",
    "repo": "docker-mods",
    "image": "mods",
    "tag": "radarr-striptracks",
    "pulls": "14.1K",
    "raw_pulls": "14090",
    "raw_pulls_all": {
      "2024-06-17": "11758",
      "2024-06-18": "12308",
      "2024-06-19": "12757",
      "2024-06-20": "13281",
      "2024-06-21": "14090"
    }
  },
  {
    "owner": "linuxserver",
    "repo": "docker-mods",
    "image": "mods",
    "tag": "lidarr-flac2mp3",
    "pulls": "8.0K",
    "raw_pulls": "8047",
    "raw_pulls_all": {
      "2024-06-17": "7202",
      "2024-06-18": "7367",
      "2024-06-19": "7567",
      "2024-06-20": "7750",
      "2024-06-21": "8047"
    }
  }
]
